[{"country": "\u00c5land", "temp": 5.957916666666666}, {"country": "Afghanistan", "temp": 13.0435}, {"country": "Africa", "temp": 23.88083333333333}, {"country": "Albania", "temp": 13.812833333333336}, {"country": "Algeria", "temp": 22.781833333333335}, {"country": "American Samoa", "temp": 26.520083333333332}, {"country": "Andorra", "temp": 11.812}, {"country": "Angola", "temp": 21.571833333333334}, {"country": "Anguilla", "temp": 26.26641666666667}, {"country": "Antigua And Barbuda", "temp": 26.052333333333333}, {"country": "Argentina", "temp": 14.795083333333332}, {"country": "Armenia", "temp": 8.213000000000001}, {"country": "Aruba", "temp": 27.488500000000002}, {"country": "Asia", "temp": 7.169833333333333}, {"country": "Australia", "temp": 21.322916666666668}, {"country": "Austria", "temp": 7.035749999999999}, {"country": "Azerbaijan", "temp": 10.891333333333334}, {"country": "Bahamas", "temp": 25.00016666666666}, {"country": "Bahrain", "temp": 25.438}, {"country": "Baker Island", "temp": 25.54058333333333}, {"country": "Bangladesh", "temp": 25.020333333333337}, {"country": "Barbados", "temp": 26.181250000000002}, {"country": "Belarus", "temp": 6.231916666666667}, {"country": "Belgium", "temp": 9.829166666666666}, {"country": "Belize", "temp": 24.782999999999998}, {"country": "Benin", "temp": 27.16175}, {"country": "Bhutan", "temp": 11.96641666666667}, {"country": "Bolivia", "temp": 20.845166666666664}, {"country": "Bonaire, Saint Eustatius And Saba", "temp": 26.759333333333334}, {"country": "Bosnia And Herzegovina", "temp": 11.704000000000002}, {"country": "Botswana", "temp": 22.124166666666667}, {"country": "Brazil", "temp": 24.639}, {"country": "British Virgin Islands", "temp": 25.99733333333333}, {"country": "Bulgaria", "temp": 11.464750000000002}, {"country": "Burkina Faso", "temp": 27.77175}, {"country": "Burma", "temp": 23.812083333333334}, {"country": "Burundi", "temp": 20.042999999999996}, {"country": "C\u00f4te D'Ivoire", "temp": 25.881249999999998}, {"country": "Cambodia", "temp": 26.789249999999996}, {"country": "Cameroon", "temp": 24.432750000000002}, {"country": "Canada", "temp": -5.952916666666668}, {"country": "Cape Verde", "temp": 24.341333333333342}, {"country": "Cayman Islands", "temp": 26.473250000000004}, {"country": "Central African Republic", "temp": 25.25191666666667}, {"country": "Chad", "temp": 26.593083333333336}, {"country": "Chile", "temp": 9.292}, {"country": "China", "temp": 6.641166666666666}, {"country": "Christmas Island", "temp": 25.82483333333333}, {"country": "Colombia", "temp": 24.425833333333333}, {"country": "Comoros", "temp": 25.625666666666675}, {"country": "Congo (Democratic Republic Of The)", "temp": 23.75758333333334}, {"country": "Congo", "temp": 24.69741666666667}, {"country": "Costa Rica", "temp": 25.368583333333333}, {"country": "Croatia", "temp": 12.430083333333334}, {"country": "Cuba", "temp": 25.144000000000005}, {"country": "Cura\u00e7ao", "temp": 26.92033333333333}, {"country": "Cyprus", "temp": 18.796333333333333}, {"country": "Czech Republic", "temp": 8.297666666666666}, {"country": "Denmark (Europe)", "temp": 8.335166666666666}, {"country": "Denmark", "temp": -17.59316666666667}, {"country": "Djibouti", "temp": 28.355916666666673}, {"country": "Dominica", "temp": 25.798000000000002}, {"country": "Dominican Republic", "temp": 25.238333333333333}, {"country": "Ecuador", "temp": 21.33441666666667}, {"country": "Egypt", "temp": 22.681083333333333}, {"country": "El Salvador", "temp": 24.643}, {"country": "Equatorial Guinea", "temp": 25.075750000000003}, {"country": "Eritrea", "temp": 26.665833333333335}, {"country": "Estonia", "temp": 5.236}, {"country": "Ethiopia", "temp": 22.658}, {"country": "Europe", "temp": 8.487499999999999}, {"country": "Falkland Islands (Islas Malvinas)", "temp": 5.699750000000001}, {"country": "Faroe Islands", "temp": 7.006500000000002}, {"country": "Federated States Of Micronesia", "temp": 27.02891666666666}, {"country": "Fiji", "temp": 25.29408333333333}, {"country": "Finland", "temp": 2.2062500000000007}, {"country": "France (Europe)", "temp": 10.921833333333332}, {"country": "France", "temp": 13.23325}, {"country": "French Guiana", "temp": 25.780749999999998}, {"country": "French Polynesia", "temp": 25.910333333333337}, {"country": "French Southern And Antarctic Lands", "temp": 3.963636363636364}, {"country": "Gabon", "temp": 24.434250000000002}, {"country": "Gambia", "temp": 27.41825}, {"country": "Gaza Strip", "temp": 19.296583333333327}, {"country": "Georgia", "temp": 7.9575000000000005}, {"country": "Germany", "temp": 8.653416666666667}, {"country": "Ghana", "temp": 26.692000000000004}, {"country": "Greece", "temp": 15.639000000000001}, {"country": "Greenland", "temp": -18.12675}, {"country": "Grenada", "temp": 26.460749999999994}, {"country": "Guadeloupe", "temp": 25.948166666666665}, {"country": "Guam", "temp": 26.87275}, {"country": "Guatemala", "temp": 22.901750000000003}, {"country": "Guernsey", "temp": 11.209333333333333}, {"country": "Guinea Bissau", "temp": 26.633583333333334}, {"country": "Guinea", "temp": 25.325583333333338}, {"country": "Guyana", "temp": 26.023750000000003}, {"country": "Haiti", "temp": 25.9605}, {"country": "Heard Island And Mcdonald Islands", "temp": 1.5833636363636365}, {"country": "Honduras", "temp": 24.371166666666664}, {"country": "Hong Kong", "temp": 23.049416666666662}, {"country": "Hungary", "temp": 10.680166666666665}, {"country": "Iceland", "temp": 1.8534999999999997}, {"country": "India", "temp": 23.659333333333326}, {"country": "Indonesia", "temp": 25.654250000000005}, {"country": "Iran", "temp": 16.908833333333327}, {"country": "Iraq", "temp": 21.31175}, {"country": "Ireland", "temp": 9.461833333333333}, {"country": "Isle Of Man", "temp": 9.429916666666665}, {"country": "Israel", "temp": 19.70975}, {"country": "Italy", "temp": 13.712583333333333}, {"country": "Jamaica", "temp": 25.723000000000003}, {"country": "Japan", "temp": 12.5895}, {"country": "Jersey", "temp": 11.209333333333333}, {"country": "Jordan", "temp": 19.401166666666672}, {"country": "Kazakhstan", "temp": 4.267416666666667}, {"country": "Kenya", "temp": 23.945416666666674}, {"country": "Kingman Reef", "temp": 26.676166666666663}, {"country": "Kiribati", "temp": 26.316166666666664}, {"country": "Kuwait", "temp": 24.617833333333333}, {"country": "Kyrgyzstan", "temp": 2.6250000000000004}, {"country": "Laos", "temp": 23.771500000000003}, {"country": "Latvia", "temp": 5.77025}, {"country": "Lebanon", "temp": 17.695249999999998}, {"country": "Lesotho", "temp": 14.00125}, {"country": "Liberia", "temp": 25.319166666666664}, {"country": "Libya", "temp": 21.881249999999998}, {"country": "Liechtenstein", "temp": 5.435499999999998}, {"country": "Lithuania", "temp": 6.466666666666666}, {"country": "Luxembourg", "temp": 9.560083333333331}, {"country": "Macau", "temp": 22.817500000000006}, {"country": "Macedonia", "temp": 11.551083333333333}, {"country": "Madagascar", "temp": 22.506666666666664}, {"country": "Malawi", "temp": 21.01108333333334}, {"country": "Malaysia", "temp": 25.91025}, {"country": "Mali", "temp": 27.8955}, {"country": "Malta", "temp": 19.21333333333333}, {"country": "Martinique", "temp": 25.798000000000002}, {"country": "Mauritania", "temp": 27.309750000000005}, {"country": "Mauritius", "temp": 23.366416666666666}, {"country": "Mayotte", "temp": 26.26275}, {"country": "Mexico", "temp": 21.256749999999997}, {"country": "Moldova", "temp": 9.625083333333333}, {"country": "Monaco", "temp": 9.813999999999998}, {"country": "Mongolia", "temp": -0.8249166666666657}, {"country": "Montenegro", "temp": 11.558666666666667}, {"country": "Montserrat", "temp": 25.984583333333333}, {"country": "Morocco", "temp": 17.952916666666667}, {"country": "Mozambique", "temp": 23.407416666666673}, {"country": "Namibia", "temp": 20.434}, {"country": "Nepal", "temp": 14.651250000000003}, {"country": "Netherlands (Europe)", "temp": 9.475666666666665}, {"country": "Netherlands", "temp": 9.853333333333333}, {"country": "New Caledonia", "temp": 23.262583333333335}, {"country": "New Zealand", "temp": 10.618000000000002}, {"country": "Nicaragua", "temp": 25.688000000000002}, {"country": "Niger", "temp": 26.735333333333333}, {"country": "Nigeria", "temp": 26.671999999999997}, {"country": "Niue", "temp": 25.27725}, {"country": "North America", "temp": 1.8704166666666666}, {"country": "North Korea", "temp": 7.225500000000001}, {"country": "Northern Mariana Islands", "temp": 26.87275}, {"country": "Norway", "temp": 0.9837499999999998}, {"country": "Oceania", "temp": 21.2035}, {"country": "Oman", "temp": 26.30383333333334}, {"country": "Pakistan", "temp": 19.694416666666665}, {"country": "Palau", "temp": 27.049916666666665}, {"country": "Palestina", "temp": 23.316}, {"country": "Palmyra Atoll", "temp": 26.699166666666667}, {"country": "Panama", "temp": 25.975333333333335}, {"country": "Papua New Guinea", "temp": 24.59358333333333}, {"country": "Paraguay", "temp": 23.434}, {"country": "Peru", "temp": 19.584}, {"country": "Philippines", "temp": 26.53216666666667}, {"country": "Poland", "temp": 8.127083333333333}, {"country": "Portugal", "temp": 15.066083333333331}, {"country": "Puerto Rico", "temp": 25.108333333333338}, {"country": "Qatar", "temp": 26.292999999999996}, {"country": "Reunion", "temp": 23.069416666666672}, {"country": "Romania", "temp": 9.758999999999999}, {"country": "Russia", "temp": -5.608916666666669}, {"country": "Rwanda", "temp": 19.259833333333333}, {"country": "Saint Barth\u00e9lemy", "temp": 26.26641666666667}, {"country": "Saint Kitts And Nevis", "temp": 25.4755}, {"country": "Saint Lucia", "temp": 26.327333333333332}, {"country": "Saint Martin", "temp": 26.26641666666667}, {"country": "Saint Pierre And Miquelon", "temp": 4.293333333333334}, {"country": "Saint Vincent And The Grenadines", "temp": 26.458083333333335}, {"country": "Samoa", "temp": 26.27458333333333}, {"country": "San Marino", "temp": 14.924333333333335}, {"country": "Sao Tome And Principe", "temp": 25.919833333333333}, {"country": "Saudi Arabia", "temp": 25.359166666666667}, {"country": "Senegal", "temp": 27.817083333333333}, {"country": "Serbia", "temp": 11.216416666666666}, {"country": "Seychelles", "temp": 26.509166666666673}, {"country": "Sierra Leone", "temp": 25.940583333333333}, {"country": "Singapore", "temp": 26.560166666666664}, {"country": "Sint Maarten", "temp": 26.26641666666667}, {"country": "Slovakia", "temp": 8.382249999999999}, {"country": "Slovenia", "temp": 10.637916666666666}, {"country": "Solomon Islands", "temp": 26.655}, {"country": "Somalia", "temp": 26.569916666666668}, {"country": "South Africa", "temp": 17.45116666666667}, {"country": "South America", "temp": 21.734916666666667}, {"country": "South Georgia And The South Sandwich Isla", "temp": 0.6483333333333334}, {"country": "South Korea", "temp": 12.339666666666666}, {"country": "Spain", "temp": 14.239249999999998}, {"country": "Sri Lanka", "temp": 26.974166666666665}, {"country": "Sudan", "temp": 26.820166666666665}, {"country": "Suriname", "temp": 26.283833333333337}, {"country": "Svalbard And Jan Mayen", "temp": -5.688083333333334}, {"country": "Swaziland", "temp": 19.027250000000006}, {"country": "Sweden", "temp": 3.0690000000000004}, {"country": "Switzerland", "temp": 7.730916666666668}, {"country": "Syria", "temp": 17.769583333333326}, {"country": "Taiwan", "temp": 22.03775}, {"country": "Tajikistan", "temp": 3.2042500000000005}, {"country": "Tanzania", "temp": 22.073666666666664}, {"country": "Thailand", "temp": 26.086916666666667}, {"country": "Timor Leste", "temp": 25.426666666666666}, {"country": "Togo", "temp": 26.941083333333335}, {"country": "Tonga", "temp": 23.478416666666664}, {"country": "Trinidad And Tobago", "temp": 25.967916666666667}, {"country": "Tunisia", "temp": 20.121749999999995}, {"country": "Turkey", "temp": 11.466666666666669}, {"country": "Turkmenistan", "temp": 13.65375}, {"country": "Turks And Caicas Islands", "temp": 26.359750000000005}, {"country": "Uganda", "temp": 22.967916666666667}, {"country": "Ukraine", "temp": 8.020666666666667}, {"country": "United Arab Emirates", "temp": 27.1305}, {"country": "United Kingdom (Europe)", "temp": 8.811416666666668}, {"country": "United Kingdom", "temp": 8.619166666666665}, {"country": "United States", "temp": 8.656416666666667}, {"country": "Uruguay", "temp": 17.41325}, {"country": "Uzbekistan", "temp": 11.026166666666668}, {"country": "Venezuela", "temp": 24.793499999999998}, {"country": "Vietnam", "temp": 23.94483333333333}, {"country": "Virgin Islands", "temp": 25.99733333333333}, {"country": "Western Sahara", "temp": 22.47583333333333}, {"country": "Yemen", "temp": 25.81566666666667}, {"country": "Zambia", "temp": 20.847666666666665}, {"country": "Zimbabwe", "temp": 21.258416666666673}]